django_netjsonconfig/__init__.py
django_netjsonconfig/admin.py
django_netjsonconfig/apps.py
django_netjsonconfig/models.py
django_netjsonconfig/settings.py
django_netjsonconfig/signals.py
django_netjsonconfig/urls.py
django_netjsonconfig/utils.py
django_netjsonconfig/validators.py
django_netjsonconfig/views.py
django_netjsonconfig/vpn_backends.py
django_netjsonconfig/widgets.py
django_netjsonconfig/base/__init__.py
django_netjsonconfig/base/admin.py
django_netjsonconfig/base/base.py
django_netjsonconfig/base/config.py
django_netjsonconfig/base/device.py
django_netjsonconfig/base/tag.py
django_netjsonconfig/base/template.py
django_netjsonconfig/base/vpn.py
django_netjsonconfig/controller/__init__.py
django_netjsonconfig/controller/generics.py
django_netjsonconfig/controller/urls.py
django_netjsonconfig/controller/views.py
django_netjsonconfig/fixtures/test_templates.json
django_netjsonconfig/migrations/0001_initial.py
django_netjsonconfig/migrations/0002_config_status.py
django_netjsonconfig/migrations/0003_config_last_ip.py
django_netjsonconfig/migrations/0004_config_allow_blank.py
django_netjsonconfig/migrations/0005_template_default.py
django_netjsonconfig/migrations/0006_utc_data_migration.py
django_netjsonconfig/migrations/0007_file_data_migration.py
django_netjsonconfig/migrations/0008_vpn_integration.py
django_netjsonconfig/migrations/0009_openvpn_data_migration.py
django_netjsonconfig/migrations/0010_basemodel_reorganization.py
django_netjsonconfig/migrations/0011_template_config_blank.py
django_netjsonconfig/migrations/0012_name_unique.py
django_netjsonconfig/migrations/0013_config_mac_address.py
django_netjsonconfig/migrations/0014_randomize_mac_address.py
django_netjsonconfig/migrations/0015_config_mac_address_unique.py
django_netjsonconfig/migrations/0016_vpn_dh.py
django_netjsonconfig/migrations/0017_openvpn_data_migration.py
django_netjsonconfig/migrations/0018_openvpn_disabled_attr.py
django_netjsonconfig/migrations/0019_cleanup_model_options.py
django_netjsonconfig-0.12.dist-info/LICENSE
django_netjsonconfig-0.12.dist-info/METADATA
django_netjsonconfig-0.12.dist-info/WHEEL
django_netjsonconfig-0.12.dist-info/top_level.txt
django_netjsonconfig-0.12.dist-info/RECORD
