Metadata-Version: 2.1
Name: django-netjsonconfig
Version: 0.12
Summary: Configuration manager for embedded devices, implemented as a reusable django-app
Home-page: http://netjson.org
Author: Federico Capoano
Author-email: federico.capoano@gmail.com
License: GPL3
Download-URL: https://github.com/openwisp/django-netjsonconfig/releases
Keywords: django,netjson,openwrt,networking,openwisp
Platform: Platform Independent
Classifier: Development Status :: 3 - Alpha
Classifier: Environment :: Web Environment
Classifier: Topic :: Internet :: WWW/HTTP
Classifier: Intended Audience :: Developers
Classifier: License :: OSI Approved :: GNU General Public License v3 (GPLv3)
Classifier: Operating System :: OS Independent
Classifier: Framework :: Django
Classifier: Topic :: System :: Networking
Classifier: Programming Language :: Python :: 3
Requires-Dist: django (<3.1,>=2.2)
Requires-Dist: django-model-utils (>=4.0)
Requires-Dist: netjsonconfig (<0.9.0,>=0.8.0)
Requires-Dist: django-sortedm2m (<3.1.0,>=3.0.0)
Requires-Dist: django-reversion (<3.1.0,>=3.0.5)
Requires-Dist: django-x509 (<0.7.0,>=0.6.2)
Requires-Dist: django-taggit (<1.3.0,>=0.24.0)
Requires-Dist: openwisp-utils (<0.6.0,>=0.5.0)
